ovos_tts_plugin_cotovia/__init__.py
ovos_tts_plugin_cotovia/version.py
ovos_tts_plugin_cotovia-0.4.3.dist-info/LICENSE
ovos_tts_plugin_cotovia-0.4.3.dist-info/METADATA
ovos_tts_plugin_cotovia-0.4.3.dist-info/WHEEL
ovos_tts_plugin_cotovia-0.4.3.dist-info/entry_points.txt
ovos_tts_plugin_cotovia-0.4.3.dist-info/top_level.txt
ovos_tts_plugin_cotovia-0.4.3.dist-info/zip-safe
ovos_tts_plugin_cotovia-0.4.3.dist-info/RECORD
